design/lab8_p2_3.v
`timescale 1ns / 1ps
//////////////////////////////////////////////////////////////////////////////////
// Company: 
// Engineer: 
// 
// Create Date: 2025/11/12 11:32:23
// Design Name: 
// Module Name: lab8_p2_3
// Project Name: 
// Target Devices: 
// Tool Versions: 
// Description: 
// 
// Dependencies: 
// 
// Revision:
// Revision 0.01 - File Created
// Additional Comments:
// 
//////////////////////////////////////////////////////////////////////////////////


module lab8_p2_3(
    input [4:0] x_in,
    input clk,
    input rst_n,
    output reg y_out,
    output reg [2:0] state,
    output reg [2:0] next_state
);
parameter S0 = 3'b000,  
          S1 = 3'b001,    
          S2 = 3'b010,  
          S3 = 3'b011,  
          S4 = 3'b100;  

reg [2:0] ones_count;

always @(*) begin
    ones_count = x_in[0] + x_in[1] + x_in[2] + x_in[3] + x_in[4];
end
always @(posedge clk or negedge rst_n) begin
    if (~rst_n)
        state <= S0;
    else
        state <= next_state;
end

always @(*) begin
    case (state)
        S0: next_state = (ones_count % 5 == 0) ? S0 :
                         (ones_count % 5 == 1) ? S1 :
                         (ones_count % 5 == 2) ? S2 :
                         (ones_count % 5 == 3) ? S3 : S4;
        S1: next_state = ((ones_count + 1) % 5 == 0) ? S0 :
                         ((ones_count + 1) % 5 == 1) ? S1 :
                         ((ones_count + 1) % 5 == 2) ? S2 :
                         ((ones_count + 1) % 5 == 3) ? S3 : S4;
        S2: next_state = ((ones_count + 2) % 5 == 0) ? S0 :
                         ((ones_count + 2) % 5 == 1) ? S1 :
                         ((ones_count + 2) % 5 == 2) ? S2 :
                         ((ones_count + 2) % 5 == 3) ? S3 : S4;
        S3: next_state = ((ones_count + 3) % 5 == 0) ? S0 :
                         ((ones_count + 3) % 5 == 1) ? S1 :
                         ((ones_count + 3) % 5 == 2) ? S2 :
                         ((ones_count + 3) % 5 == 3) ? S3 : S4;
        S4: next_state = ((ones_count + 4) % 5 == 0) ? S0 :
                         ((ones_count + 4) % 5 == 1) ? S1 :
                         ((ones_count + 4) % 5 == 2) ? S2 :
                         ((ones_count + 4) % 5 == 3) ? S3 : S4;
        default: next_state = S0;
    endcase
end

// 
always @(*) begin
    y_out = (state == S0);  
end

endmodule

design/lab8_p2.v
`timescale 1ns / 1ps
//simple Moore FSM to count number of 1's mod 5
module lab8_p2(
input [4:0] x_in,
input clk,rst_n,
output reg y_out,
output reg [2:0] state,next_state
    );
parameter S0=3'b000,S1=3'b001,S2=3'b010,S3=3'b011,S4=3'b100;
reg [2:0] ones_count;
always @(*) begin
    ones_count = x_in[0]+x_in[1]+x_in[2]+x_in[3]+x_in[4];
end
always @(posedge clk,negedge rst_n) begin
    if(~rst_n)
        state <= S0;
    else
        state <= next_state;
end
always @(state,x_in) begin
    case(state)
    S0: next_state = (ones_count % 5 == 0) ? S0 :
                     (ones_count % 5 == 1) ? S1 :
                     (ones_count % 5 == 2) ? S2 :
                     (ones_count % 5 == 3) ? S3 : S4;
    S1: next_state = ((ones_count + 1) % 5 == 0) ? S0 :
                     ((ones_count + 1) % 5 == 1) ? S1 :
                     ((ones_count + 1) % 5 == 2) ? S2 :
                     ((ones_count + 1) % 5 == 3) ? S3 : S4;
    S2: next_state = ((ones_count + 2) % 5 == 0) ? S0 :
                     ((ones_count + 2) % 5 == 1) ? S1 :
                     ((ones_count + 2) % 5 == 2) ? S2 :
                     ((ones_count + 2) % 5 == 3) ? S3 : S4;
    S3: next_state = ((ones_count + 3) % 5 == 0) ? S0 :
                     ((ones_count + 3) % 5 == 1) ? S1 :
                     ((ones_count + 3) % 5 == 2) ? S2 :
                     ((ones_count + 3) % 5 == 3) ? S3 : S4;
    S4: next_state = ((ones_count + 4) % 5 == 0) ? S0 :
                     ((ones_count + 4) % 5 == 1) ? S1 :
                     ((ones_count + 4) % 5 == 2) ? S2 :
                     ((ones_count + 4) % 5 == 3) ? S3 : S4;
    default: next_state = S0;
    endcase
    y_out = (state == S0);
    end
endmodule

simulation/tb_lab8_p2.v
`timescale 1ns / 1ps
`include "../Design/lab8_p2.v"
`include "../Design/lab8_p2_3.v"

\\effs
module tb_lab8_p2;

reg [4:0] x_in;
reg clk;
reg rst_n;

wire y_out1,y_out2;
wire [2:0] state1,state2;   
wire [2:0] next_state1,next_state2;

lab8_p2 u1 (
    .x_in(x_in),
    .clk(clk),
    .rst_n(rst_n),
    .y_out(y_out1),
    .state(state1),
    .next_state(next_state1)
);

lab8_p2_3 u2 (
    .x_in(x_in),
    .clk(clk),
    .rst_n(rst_n),
    .y_out(y_out2),
    .state(state2),
    .next_state(next_state2)
);
initial begin
    clk = 0;
    forever #5 clk = ~clk;
end

initial begin
    rst_n = 0;
    x_in = 5'b00000;
    #20;
    
    rst_n = 1;
    #10;
    
    x_in = 5'b11111;
    #10;
    
    x_in = 5'b10101;
    #10;
    
    x_in = 5'b10001;
    #10;
    
    x_in = 5'b00000;
    #10;
    
    x_in = 5'b11110;
    #10;
    
    x_in = 5'b00001;
    #10;
    
    #20;
    $finish;
end

initial begin
    $dumpfile("tb_lab8_p2.vcd");
    $dumpvars(0,tb_lab8_p2);
end

endmodule

simulation/tb_lab8_p2.vcd
$date
	Wed Nov 19 12:00:25 2025
$end
$version
	Icarus Verilog
$end
$timescale
	1ps
$end
$scope module tb_lab8_p2 $end
$var wire 1 ! y_out2 $end
$var wire 1 " y_out1 $end
$var wire 3 # state2 [2:0] $end
$var wire 3 $ state1 [2:0] $end
$var wire 3 % next_state2 [2:0] $end
$var wire 3 & next_state1 [2:0] $end
$var reg 1 ' clk $end
$var reg 1 ( rst_n $end
$var reg 5 ) x_in [4:0] $end
$scope module u1 $end
$var wire 1 ' clk $end
$var wire 1 ( rst_n $end
$var wire 5 * x_in [4:0] $end
$var reg 3 + next_state [2:0] $end
$var reg 3 , ones_count [2:0] $end
$var reg 3 - state [2:0] $end
$var reg 1 " y_out $end
$upscope $end
$scope module u2 $end
$var wire 1 ' clk $end
$var wire 1 ( rst_n $end
$var wire 5 . x_in [4:0] $end
$var reg 3 / next_state [2:0] $end
$var reg 3 0 ones_count [2:0] $end
$var reg 3 1 state [2:0] $end
$var reg 1 ! y_out $end
$upscope $end
$upscope $end
$enddefinitions $end
#0
$dumpvars
b0 1
b0 0
b0 /
b0 .
b0 -
b0 ,
b0 +
b0 *
b0 )
0(
0'
b0 &
b0 %
b0 $
b0 #
1"
1!
$end
#5000
1'
#10000
0'
#15000
1'
#20000
0'
1(
#25000
1'
#30000
b101 ,
b101 0
0'
b11111 )
b11111 *
b11111 .
#35000
1'
#40000
b11 %
b11 /
b11 &
b11 +
b11 0
b11 ,
0'
b10101 )
b10101 *
b10101 .
#45000
0!
b1 %
b1 /
0"
b1 &
b1 +
b11 #
b11 1
b11 $
b11 -
1'
#50000
b0 %
b0 /
b0 &
b0 +
b10 ,
b10 0
0'
b10001 )
b10001 *
b10001 .
#55000
1"
b10 &
b10 +
1!
b10 %
b10 /
b0 $
b0 -
b0 #
b0 1
1'
#60000
b0 %
b0 /
b0 &
b0 +
b0 0
b0 ,
0'
b0 )
b0 *
b0 .
#65000
1'
#70000
b100 %
b100 /
b100 &
b100 +
b100 ,
b100 0
0'
b11110 )
b11110 *
b11110 .
#75000
0"
b11 &
b11 +
0!
b11 %
b11 /
b100 $
b100 -
b100 #
b100 1
1'
#80000
b0 %
b0 /
b0 &
b0 +
b1 0
b1 ,
0'
b1 )
b1 *
b1 .
#85000
1!
b1 %
b1 /
1"
b1 &
b1 +
b0 #
b0 1
b0 $
b0 -
1'
#90000
0'
#95000
0"
b10 &
b10 +
0!
b10 %
b10 /
b1 $
b1 -
b1 #
b1 1
1'
#100000
0'
#105000
b11 %
b11 /
b11 &
b11 +
b10 #
b10 1
b10 $
b10 -
1'
